{"FileName": "2353.png", "NumOfAnno": 7, "Annotations": [{"isProtected": false, "ID": 652231476823842176, "BoundingBox": [414, 4, 564, 148], "classname": "face_with_mask", "Confidence": 1, "Attributes": {}}, {"isProtected": false, "ID": 80413612127324112, "BoundingBox": [148, 363, 244, 477], "classname": "face_with_mask", "Confidence": 1, "Attributes": {}}, {"isProtected": false, "ID": 225064121956410336, "BoundingBox": [1050, 101, 1168, 260], "classname": "face_with_mask", "Confidence": 1, "Attributes": {}}, {"isProtected": false, "ID": 573559478970363328, "BoundingBox": [415, 91, 489, 148], "classname": "mask_surgical", "Confidence": 1, "Attributes": {}}, {"isProtected": false, "ID": 629172005295362432, "BoundingBox": [1057, 168, 1157, 257], "classname": "mask_surgical", "Confidence": 1, "Attributes": {}}, {"isProtected": false, "ID": 151920383152937088, "BoundingBox": [200, 425, 235, 475], "classname": "mask_colorful", "Confidence": 1, "Attributes": {}}, {"isProtected": false, "ID": 191909668252369088, "BoundingBox": [410, 6, 565, 73], "classname": "hat", "Confidence": 1, "Attributes": {}}]}