{"FileName": "2365.png", "NumOfAnno": 4, "Annotations": [{"isProtected": false, "ID": 843417380003174272, "BoundingBox": [430, 38, 535, 201], "classname": "face_with_mask", "Confidence": 1, "Attributes": {}}, {"isProtected": false, "ID": 658983727591064064, "BoundingBox": [713, 71, 796, 184], "classname": "face_with_mask", "Confidence": 1, "Attributes": {}}, {"isProtected": false, "ID": 261151118509205152, "BoundingBox": [436, 123, 524, 196], "classname": "mask_surgical", "Confidence": 1, "Attributes": {}}, {"isProtected": false, "ID": 726413704629585152, "BoundingBox": [722, 124, 778, 182], "classname": "mask_surgical", "Confidence": 1, "Attributes": {}}]}