{"FileName": "2380.png", "NumOfAnno": 4, "Annotations": [{"isProtected": false, "ID": 719931173001160448, "BoundingBox": [372, 51, 468, 162], "classname": "face_other_covering", "Confidence": 1, "Attributes": {}}, {"isProtected": false, "ID": 570237097011738304, "BoundingBox": [78, 254, 175, 373], "classname": "face_other_covering", "Confidence": 1, "Attributes": {}}, {"isProtected": false, "ID": 135320877816720864, "BoundingBox": [366, 45, 473, 171], "classname": "helmet", "Confidence": 1, "Attributes": {}}, {"isProtected": false, "ID": 995196595649067264, "BoundingBox": [81, 254, 164, 311], "classname": "hat", "Confidence": 1, "Attributes": {}}]}