{"FileName": "2861.png", "NumOfAnno": 3, "Annotations": [{"isProtected": false, "ID": 566682347773781696, "BoundingBox": [193, 3, 562, 517], "classname": "face_with_mask", "Confidence": 1, "Attributes": {}}, {"isProtected": false, "ID": 402953045065771776, "BoundingBox": [236, 282, 541, 513], "classname": "mask_colorful", "Confidence": 1, "Attributes": {}}, {"isProtected": false, "ID": 439628629864217344, "BoundingBox": [206, 3, 560, 223], "classname": "hat", "Confidence": 1, "Attributes": {}}]}