{"FileName": "2997.png", "NumOfAnno": 6, "Annotations": [{"isProtected": false, "ID": 3280914839252413, "BoundingBox": [399, 195, 453, 259], "classname": "face_with_mask", "Confidence": 1, "Attributes": {}}, {"isProtected": false, "ID": 744868026053570688, "BoundingBox": [188, 174, 238, 237], "classname": "face_with_mask", "Confidence": 1, "Attributes": {}}, {"isProtected": false, "ID": 805829461257874944, "BoundingBox": [196, 203, 235, 236], "classname": "mask_surgical", "Confidence": 1, "Attributes": {}}, {"isProtected": false, "ID": 205495779971905600, "BoundingBox": [398, 224, 437, 258], "classname": "mask_surgical", "Confidence": 1, "Attributes": {}}, {"isProtected": false, "ID": 997761506821632768, "BoundingBox": [89, 195, 123, 236], "classname": "face_no_mask", "Confidence": 1, "Attributes": {}}, {"isProtected": false, "ID": 684427200717871616, "BoundingBox": [318, 191, 354, 235], "classname": "face_no_mask", "Confidence": 1, "Attributes": {}}]}