{"FileName": "3026.png", "NumOfAnno": 3, "Annotations": [{"isProtected": false, "ID": 143451975275016192, "BoundingBox": [129, 37, 419, 375], "classname": "face_other_covering", "Confidence": 1, "Attributes": {}}, {"isProtected": false, "ID": 276537159225579200, "BoundingBox": [130, 63, 408, 306], "classname": "goggles", "Confidence": 1, "Attributes": {}}, {"isProtected": false, "ID": 397621523592554880, "BoundingBox": [211, 42, 393, 190], "classname": "hat", "Confidence": 1, "Attributes": {}}]}