{"FileName": "3334.png", "NumOfAnno": 11, "Annotations": [{"isProtected": false, "ID": 354653770615648832, "BoundingBox": [720, 4, 811, 110], "classname": "face_with_mask", "Confidence": 1, "Attributes": {}}, {"isProtected": false, "ID": 119616480070658944, "BoundingBox": [271, 52, 406, 195], "classname": "face_no_mask", "Confidence": 1, "Attributes": {}}, {"isProtected": false, "ID": 943494244608278144, "BoundingBox": [729, 47, 803, 100], "classname": "mask_surgical", "Confidence": 1, "Attributes": {}}, {"isProtected": false, "ID": 819062652763328640, "BoundingBox": [2, 0, 72, 110], "classname": "face_no_mask", "Confidence": 1, "Attributes": {}}, {"isProtected": false, "ID": 100538282064183808, "BoundingBox": [578, 105, 621, 159], "classname": "face_no_mask", "Confidence": 1, "Attributes": {}}, {"isProtected": false, "ID": 663294918747592576, "BoundingBox": [930, 162, 964, 187], "classname": "mask_surgical", "Confidence": 1, "Attributes": {}}, {"isProtected": false, "ID": 868278827982594176, "BoundingBox": [924, 119, 980, 189], "classname": "face_with_mask", "Confidence": 1, "Attributes": {}}, {"isProtected": false, "ID": 807156324649137024, "BoundingBox": [413, 144, 474, 230], "classname": "face_other_covering", "Confidence": 1, "Attributes": {}}, {"isProtected": false, "ID": 916577194387883520, "BoundingBox": [1030, 90, 1089, 156], "classname": "face_other_covering", "Confidence": 1, "Attributes": {}}, {"isProtected": false, "ID": 548144108604972288, "BoundingBox": [409, 142, 477, 198], "classname": "hat", "Confidence": 1, "Attributes": {}}, {"isProtected": false, "ID": 365186041721005248, "BoundingBox": [1026, 89, 1089, 134], "classname": "hat", "Confidence": 1, "Attributes": {}}]}