{"FileName": "3448.png", "NumOfAnno": 6, "Annotations": [{"isProtected": false, "ID": 879643997456812288, "BoundingBox": [580, 91, 752, 316], "classname": "face_other_covering", "Confidence": 1, "Attributes": {}}, {"isProtected": false, "ID": 177240604705908960, "BoundingBox": [161, 0, 476, 271], "classname": "face_other_covering", "Confidence": 1, "Attributes": {}}, {"isProtected": false, "ID": 809190199687955456, "BoundingBox": [168, 8, 467, 347], "classname": "hijab_niqab", "Confidence": 1, "Attributes": {}}, {"isProtected": false, "ID": 185047413292395264, "BoundingBox": [550, 88, 759, 360], "classname": "scarf_bandana", "Confidence": 1, "Attributes": {}}, {"isProtected": false, "ID": 772350579605744256, "BoundingBox": [424, 118, 471, 188], "classname": "eyeglasses", "Confidence": 1, "Attributes": {}}, {"isProtected": false, "ID": 615728324306727296, "BoundingBox": [594, 155, 724, 219], "classname": "eyeglasses", "Confidence": 1, "Attributes": {}}]}