{"FileName": "3496.png", "NumOfAnno": 4, "Annotations": [{"isProtected": false, "ID": 146617565525083200, "BoundingBox": [209, 79, 428, 352], "classname": "face_with_mask", "Confidence": 1, "Attributes": {}}, {"isProtected": false, "ID": 262175060395364192, "BoundingBox": [209, 180, 388, 235], "classname": "eyeglasses", "Confidence": 1, "Attributes": {}}, {"isProtected": false, "ID": 710600571770843904, "BoundingBox": [223, 216, 379, 345], "classname": "mask_colorful", "Confidence": 1, "Attributes": {}}, {"isProtected": false, "ID": 920169121208882560, "BoundingBox": [209, 79, 428, 223], "classname": "hat", "Confidence": 1, "Attributes": {}}]}