{"FileName": "3511.png", "NumOfAnno": 10, "Annotations": [{"isProtected": false, "ID": 805273420755467776, "BoundingBox": [314, 88, 505, 326], "classname": "face_with_mask", "Confidence": 1, "Attributes": {}}, {"isProtected": false, "ID": 288387104734066368, "BoundingBox": [69, 80, 288, 337], "classname": "face_no_mask", "Confidence": 1, "Attributes": {}}, {"isProtected": false, "ID": 240778950785434112, "BoundingBox": [321, 196, 482, 318], "classname": "mask_surgical", "Confidence": 1, "Attributes": {}}, {"isProtected": false, "ID": 810279620939188480, "BoundingBox": [323, 163, 485, 217], "classname": "eyeglasses", "Confidence": 1, "Attributes": {}}, {"isProtected": false, "ID": 903614283994710272, "BoundingBox": [236, 39, 338, 154], "classname": "face_with_mask", "Confidence": 1, "Attributes": {}}, {"isProtected": false, "ID": 375715385644413120, "BoundingBox": [472, 196, 529, 313], "classname": "face_with_mask", "Confidence": 1, "Attributes": {}}, {"isProtected": false, "ID": 163123207521954752, "BoundingBox": [250, 93, 339, 146], "classname": "mask_colorful", "Confidence": 1, "Attributes": {}}, {"isProtected": false, "ID": 422483167705760128, "BoundingBox": [470, 260, 525, 314], "classname": "mask_colorful", "Confidence": 1, "Attributes": {}}, {"isProtected": false, "ID": 997666601220569088, "BoundingBox": [250, 202, 329, 350], "classname": "face_no_mask", "Confidence": 1, "Attributes": {}}, {"isProtected": false, "ID": 133433759223866128, "BoundingBox": [583, 67, 945, 575], "classname": "face_no_mask", "Confidence": 1, "Attributes": {}}]}