{"FileName": "3553.png", "NumOfAnno": 3, "Annotations": [{"isProtected": false, "ID": 43052571907714384, "BoundingBox": [180, 69, 370, 336], "classname": "face_with_mask", "Confidence": 1, "Attributes": {}}, {"isProtected": false, "ID": 718103921749238784, "BoundingBox": [223, 199, 358, 332], "classname": "mask_colorful", "Confidence": 1, "Attributes": {}}, {"isProtected": false, "ID": 797449192767951872, "BoundingBox": [185, 74, 366, 195], "classname": "hat", "Confidence": 1, "Attributes": {}}]}