{"FileName": "3732.png", "NumOfAnno": 15, "Annotations": [{"isProtected": false, "ID": 445115887518924288, "BoundingBox": [205, 77, 289, 180], "classname": "face_with_mask", "Confidence": 1, "Attributes": {}}, {"isProtected": false, "ID": 732283301596268928, "BoundingBox": [40, 87, 118, 195], "classname": "face_with_mask", "Confidence": 1, "Attributes": {}}, {"isProtected": false, "ID": 387304663313011136, "BoundingBox": [73, 154, 116, 194], "classname": "mask_surgical", "Confidence": 1, "Attributes": {}}, {"isProtected": false, "ID": 636515454204539904, "BoundingBox": [224, 151, 270, 172], "classname": "mask_surgical", "Confidence": 1, "Attributes": {}}, {"isProtected": false, "ID": 196773679506257472, "BoundingBox": [246, 147, 286, 162], "classname": "eyeglasses", "Confidence": 1, "Attributes": {}}, {"isProtected": false, "ID": 703470105261734400, "BoundingBox": [297, 64, 407, 166], "classname": "face_other_covering", "Confidence": 1, "Attributes": {}}, {"isProtected": false, "ID": 240596831924866592, "BoundingBox": [296, 9, 321, 30], "classname": "mask_surgical", "Confidence": 1, "Attributes": {}}, {"isProtected": false, "ID": 662466404417443584, "BoundingBox": [428, 11, 456, 37], "classname": "mask_surgical", "Confidence": 1, "Attributes": {}}, {"isProtected": false, "ID": 60622157680372600, "BoundingBox": [297, 55, 404, 163], "classname": "hood", "Confidence": 1, "Attributes": {}}, {"isProtected": false, "ID": 628167712595871616, "BoundingBox": [280, 0, 326, 31], "classname": "hood", "Confidence": 1, "Attributes": {}}, {"isProtected": false, "ID": 477052406064604864, "BoundingBox": [420, 0, 472, 44], "classname": "hood", "Confidence": 1, "Attributes": {}}, {"isProtected": false, "ID": 428100850820722368, "BoundingBox": [420, 0, 467, 13], "classname": "goggles", "Confidence": 1, "Attributes": {}}, {"isProtected": false, "ID": 375025743995929024, "BoundingBox": [309, 132, 344, 162], "classname": "goggles", "Confidence": 1, "Attributes": {}}, {"isProtected": false, "ID": 490606398853714368, "BoundingBox": [274, 0, 330, 35], "classname": "face_with_mask", "Confidence": 1, "Attributes": {}}, {"isProtected": false, "ID": 429018468930880000, "BoundingBox": [418, 2, 471, 48], "classname": "face_with_mask", "Confidence": 1, "Attributes": {}}]}