{"FileName": "3775.png", "NumOfAnno": 4, "Annotations": [{"isProtected": false, "ID": 822935321149030784, "BoundingBox": [618, 323, 750, 464], "classname": "face_with_mask", "Confidence": 1, "Attributes": {}}, {"isProtected": false, "ID": 168447147727615584, "BoundingBox": [675, 382, 747, 461], "classname": "mask_colorful", "Confidence": 1, "Attributes": {}}, {"isProtected": false, "ID": 535301331515366080, "BoundingBox": [126, 181, 254, 344], "classname": "face_with_mask", "Confidence": 1, "Attributes": {}}, {"isProtected": false, "ID": 426213311118485376, "BoundingBox": [129, 273, 180, 341], "classname": "mask_surgical", "Confidence": 1, "Attributes": {}}]}