{"FileName": "4024.png", "NumOfAnno": 6, "Annotations": [{"isProtected": false, "ID": 120890060258068928, "BoundingBox": [287, 24, 519, 354], "classname": "face_with_mask", "Confidence": 1, "Attributes": {}}, {"isProtected": false, "ID": 575029567866530560, "BoundingBox": [47, 44, 232, 319], "classname": "face_with_mask", "Confidence": 1, "Attributes": {}}, {"isProtected": false, "ID": 370646716784970944, "BoundingBox": [52, 177, 216, 314], "classname": "mask_surgical", "Confidence": 1, "Attributes": {}}, {"isProtected": false, "ID": 795874102976729344, "BoundingBox": [295, 203, 477, 351], "classname": "mask_surgical", "Confidence": 1, "Attributes": {}}, {"isProtected": false, "ID": 858029287253474432, "BoundingBox": [57, 44, 231, 180], "classname": "hair_net", "Confidence": 1, "Attributes": {}}, {"isProtected": false, "ID": 210645320691423936, "BoundingBox": [294, 23, 513, 170], "classname": "hair_net", "Confidence": 1, "Attributes": {}}]}