{"FileName": "4073.png", "NumOfAnno": 8, "Annotations": [{"isProtected": false, "ID": 579933392695923328, "BoundingBox": [454, 23, 974, 662], "classname": "face_with_mask", "Confidence": 1, "Attributes": {}}, {"isProtected": false, "ID": 837778115048193280, "BoundingBox": [459, 300, 888, 661], "classname": "mask_surgical", "Confidence": 1, "Attributes": {}}, {"isProtected": false, "ID": 259294676635694048, "BoundingBox": [260, 240, 299, 298], "classname": "face_other_covering", "Confidence": 1, "Attributes": {}}, {"isProtected": false, "ID": 44763920320880168, "BoundingBox": [981, 523, 1038, 581], "classname": "face_other_covering", "Confidence": 1, "Attributes": {}}, {"isProtected": false, "ID": 749595128263719552, "BoundingBox": [258, 234, 301, 271], "classname": "hat", "Confidence": 1, "Attributes": {}}, {"isProtected": false, "ID": 180016608055362688, "BoundingBox": [976, 522, 1035, 559], "classname": "hat", "Confidence": 1, "Attributes": {}}, {"isProtected": false, "ID": 340331723639579392, "BoundingBox": [123, 217, 175, 283], "classname": "face_no_mask", "Confidence": 1, "Attributes": {}}, {"isProtected": false, "ID": 886560499475616512, "BoundingBox": [312, 310, 364, 376], "classname": "face_no_mask", "Confidence": 1, "Attributes": {}}]}