{"FileName": "4403.png", "NumOfAnno": 3, "Annotations": [{"isProtected": false, "ID": 176450988245946752, "BoundingBox": [173, 113, 548, 588], "classname": "face_with_mask", "Confidence": 1, "Attributes": {}}, {"isProtected": false, "ID": 812718904276269184, "BoundingBox": [211, 303, 504, 577], "classname": "mask_colorful", "Confidence": 1, "Attributes": {}}, {"isProtected": false, "ID": 61479549642683872, "BoundingBox": [125, 70, 636, 600], "classname": "hood", "Confidence": 1, "Attributes": {}}]}