{"FileName": "4462.png", "NumOfAnno": 5, "Annotations": [{"isProtected": false, "ID": 773479115324048000, "BoundingBox": [278, 23, 342, 103], "classname": "face_with_mask", "Confidence": 1, "Attributes": {}}, {"isProtected": false, "ID": 419014826867591616, "BoundingBox": [414, 100, 473, 174], "classname": "face_with_mask", "Confidence": 1, "Attributes": {}}, {"isProtected": false, "ID": 5191024645840425, "BoundingBox": [424, 123, 473, 141], "classname": "sunglasses", "Confidence": 1, "Attributes": {}}, {"isProtected": false, "ID": 929291920047902720, "BoundingBox": [288, 62, 340, 100], "classname": "mask_surgical", "Confidence": 1, "Attributes": {}}, {"isProtected": false, "ID": 756501140795261184, "BoundingBox": [423, 140, 469, 170], "classname": "mask_surgical", "Confidence": 1, "Attributes": {}}]}