{"FileName": "4516.png", "NumOfAnno": 7, "Annotations": [{"isProtected": false, "ID": 862696871435529344, "BoundingBox": [105, 265, 185, 349], "classname": "face_with_mask", "Confidence": 1, "Attributes": {}}, {"isProtected": false, "ID": 673292379702619008, "BoundingBox": [190, 298, 244, 373], "classname": "face_with_mask", "Confidence": 1, "Attributes": {}}, {"isProtected": false, "ID": 602617437458915968, "BoundingBox": [544, 246, 610, 327], "classname": "face_with_mask", "Confidence": 1, "Attributes": {}}, {"isProtected": false, "ID": 163191852650713664, "BoundingBox": [546, 278, 596, 322], "classname": "mask_colorful", "Confidence": 1, "Attributes": {}}, {"isProtected": false, "ID": 588558278240718336, "BoundingBox": [140, 303, 184, 345], "classname": "mask_surgical", "Confidence": 1, "Attributes": {}}, {"isProtected": false, "ID": 855957042091045760, "BoundingBox": [199, 328, 243, 367], "classname": "mask_surgical", "Confidence": 1, "Attributes": {}}, {"isProtected": false, "ID": 721933536804632960, "BoundingBox": [144, 291, 178, 306], "classname": "eyeglasses", "Confidence": 1, "Attributes": {}}]}