{"FileName": "4565.png", "NumOfAnno": 6, "Annotations": [{"isProtected": false, "ID": 627685658414131456, "BoundingBox": [136, 147, 230, 276], "classname": "face_with_mask", "Confidence": 1, "Attributes": {}}, {"isProtected": false, "ID": 516809840912648128, "BoundingBox": [419, 144, 497, 260], "classname": "face_with_mask", "Confidence": 1, "Attributes": {}}, {"isProtected": false, "ID": 674774622555068928, "BoundingBox": [501, 164, 602, 290], "classname": "face_with_mask", "Confidence": 1, "Attributes": {}}, {"isProtected": false, "ID": 809883543134145024, "BoundingBox": [158, 223, 229, 271], "classname": "mask_surgical", "Confidence": 1, "Attributes": {}}, {"isProtected": false, "ID": 936954082647187456, "BoundingBox": [422, 205, 485, 252], "classname": "mask_surgical", "Confidence": 1, "Attributes": {}}, {"isProtected": false, "ID": 885844811314386048, "BoundingBox": [503, 224, 547, 287], "classname": "mask_surgical", "Confidence": 1, "Attributes": {}}]}