{"FileName": "4930.png", "NumOfAnno": 4, "Annotations": [{"isProtected": false, "ID": 316747842043641792, "BoundingBox": [31, 37, 214, 305], "classname": "face_other_covering", "Confidence": 1, "Attributes": {}}, {"isProtected": false, "ID": 973356829743683072, "BoundingBox": [209, 56, 411, 326], "classname": "face_other_covering", "Confidence": 1, "Attributes": {}}, {"isProtected": false, "ID": 945001691396701952, "BoundingBox": [0, 39, 210, 402], "classname": "hijab_niqab", "Confidence": 1, "Attributes": {}}, {"isProtected": false, "ID": 794487998048749440, "BoundingBox": [150, 57, 442, 404], "classname": "hijab_niqab", "Confidence": 1, "Attributes": {}}]}