{"FileName": "4965.png", "NumOfAnno": 4, "Annotations": [{"isProtected": false, "ID": 507379421854887808, "BoundingBox": [130, 217, 243, 318], "classname": "face_with_mask", "Confidence": 1, "Attributes": {}}, {"isProtected": false, "ID": 917316932875849472, "BoundingBox": [502, 20, 583, 142], "classname": "face_with_mask", "Confidence": 1, "Attributes": {}}, {"isProtected": false, "ID": 618872436898082944, "BoundingBox": [171, 260, 242, 314], "classname": "mask_surgical", "Confidence": 1, "Attributes": {}}, {"isProtected": false, "ID": 560219173559384000, "BoundingBox": [502, 83, 542, 133], "classname": "mask_surgical", "Confidence": 1, "Attributes": {}}]}