{"FileName": "5042.jpg", "NumOfAnno": 10, "Annotations": [{"isProtected": false, "ID": 780440868301188992, "BoundingBox": [272, 49, 418, 241], "classname": "face_with_mask", "Confidence": 1, "Attributes": {}}, {"isProtected": false, "ID": 420331242588017664, "BoundingBox": [417, 0, 613, 236], "classname": "face_other_covering", "Confidence": 1, "Attributes": {}}, {"isProtected": false, "ID": 76104166519453072, "BoundingBox": [134, 184, 296, 438], "classname": "face_other_covering", "Confidence": 1, "Attributes": {}}, {"isProtected": false, "ID": 253329459422916192, "BoundingBox": [375, 273, 542, 445], "classname": "face_other_covering", "Confidence": 1, "Attributes": {}}, {"isProtected": false, "ID": 627250385703362816, "BoundingBox": [122, 189, 310, 355], "classname": "hat", "Confidence": 1, "Attributes": {}}, {"isProtected": false, "ID": 396085012062372992, "BoundingBox": [361, 266, 517, 374], "classname": "hat", "Confidence": 1, "Attributes": {}}, {"isProtected": false, "ID": 113335776195999776, "BoundingBox": [278, 133, 410, 237], "classname": "mask_surgical", "Confidence": 1, "Attributes": {}}, {"isProtected": false, "ID": 219351438293158272, "BoundingBox": [415, 4, 633, 141], "classname": "hat", "Confidence": 1, "Attributes": {}}, {"isProtected": false, "ID": 473874405754617280, "BoundingBox": [0, 141, 120, 245], "classname": "hat", "Confidence": 1, "Attributes": {}}, {"isProtected": false, "ID": 251622629741087392, "BoundingBox": [0, 141, 123, 377], "classname": "face_other_covering", "Confidence": 1, "Attributes": {}}]}