{"FileName": "5121.jpg", "NumOfAnno": 13, "Annotations": [{"isProtected": false, "ID": 719608531640266496, "BoundingBox": [217, 75, 325, 235], "classname": "face_with_mask", "Confidence": 1, "Attributes": {}}, {"isProtected": false, "ID": 790842152028732160, "BoundingBox": [46, 88, 128, 211], "classname": "face_with_mask", "Confidence": 1, "Attributes": {}}, {"isProtected": false, "ID": 745448624666388224, "BoundingBox": [385, 84, 485, 226], "classname": "face_with_mask", "Confidence": 1, "Attributes": {}}, {"isProtected": false, "ID": 174123031250238432, "BoundingBox": [218, 144, 322, 175], "classname": "eyeglasses", "Confidence": 1, "Attributes": {}}, {"isProtected": false, "ID": 430763636122158592, "BoundingBox": [47, 154, 127, 210], "classname": "mask_colorful", "Confidence": 1, "Attributes": {}}, {"isProtected": false, "ID": 854594087501333248, "BoundingBox": [225, 165, 318, 234], "classname": "mask_surgical", "Confidence": 1, "Attributes": {}}, {"isProtected": false, "ID": 342528352746383168, "BoundingBox": [399, 167, 482, 223], "classname": "mask_surgical", "Confidence": 1, "Attributes": {}}, {"isProtected": false, "ID": 263230803700137856, "BoundingBox": [317, 99, 354, 155], "classname": "mask_surgical", "Confidence": 1, "Attributes": {}}, {"isProtected": false, "ID": 977340676548196736, "BoundingBox": [109, 61, 143, 95], "classname": "mask_surgical", "Confidence": 1, "Attributes": {}}, {"isProtected": false, "ID": 778901186804275456, "BoundingBox": [162, 130, 207, 159], "classname": "mask_surgical", "Confidence": 1, "Attributes": {}}, {"isProtected": false, "ID": 983481391981392896, "BoundingBox": [251, 14, 352, 142], "classname": "face_with_mask", "Confidence": 1, "Attributes": {}}, {"isProtected": false, "ID": 994244851756081536, "BoundingBox": [153, 62, 226, 156], "classname": "face_with_mask", "Confidence": 1, "Attributes": {}}, {"isProtected": false, "ID": 223539688902270496, "BoundingBox": [78, 26, 140, 93], "classname": "face_with_mask", "Confidence": 1, "Attributes": {}}]}