{"FileName": "5144.jpg", "NumOfAnno": 3, "Annotations": [{"isProtected": false, "ID": 42559377546771968, "BoundingBox": [186, 43, 497, 481], "classname": "face_with_mask", "Confidence": 1, "Attributes": {}}, {"isProtected": false, "ID": 779952667093618048, "BoundingBox": [208, 269, 464, 479], "classname": "mask_colorful", "Confidence": 1, "Attributes": {}}, {"isProtected": false, "ID": 14378925337110826, "BoundingBox": [195, 214, 458, 311], "classname": "sunglasses", "Confidence": 1, "Attributes": {}}]}