{"FileName": "5271.jpg", "NumOfAnno": 4, "Annotations": [{"isProtected": false, "ID": 430863361238269952, "BoundingBox": [401, 192, 639, 427], "classname": "face_with_mask_incorrect", "Confidence": 1, "Attributes": {}}, {"isProtected": false, "ID": 426920020615269248, "BoundingBox": [439, 288, 626, 424], "classname": "mask_surgical", "Confidence": 1, "Attributes": {}}, {"isProtected": false, "ID": 345493452087015424, "BoundingBox": [452, 259, 630, 314], "classname": "eyeglasses", "Confidence": 1, "Attributes": {}}, {"isProtected": false, "ID": 356529570630450240, "BoundingBox": [303, 34, 737, 234], "classname": "hat", "Confidence": 1, "Attributes": {}}]}