{"FileName": "5433.jpg", "NumOfAnno": 3, "Annotations": [{"isProtected": false, "ID": 695845682472195456, "BoundingBox": [332, 159, 487, 324], "classname": "face_shield", "Confidence": 1, "Attributes": {}}, {"isProtected": false, "ID": 598018394121960704, "BoundingBox": [348, 224, 466, 318], "classname": "mask_surgical", "Confidence": 1, "Attributes": {}}, {"isProtected": false, "ID": 672248899846581376, "BoundingBox": [330, 118, 483, 324], "classname": "face_with_mask", "Confidence": 1, "Attributes": {}}]}